amirispy/__init__.py
amirispy/scripts/__init__.py
amirispy/scripts/amiris.py
amirispy/scripts/subcommands/__init__.py
amirispy/scripts/subcommands/batch.py
amirispy/scripts/subcommands/compare.py
amirispy/scripts/subcommands/download.py
amirispy/scripts/subcommands/run.py
amirispy/source/__init__.py
amirispy/source/cli.py
amirispy/source/exception.py
amirispy/source/fameio_calls.py
amirispy/source/file_comparison.py
amirispy/source/files.py
amirispy/source/java.py
amirispy/source/logs.py
amirispy-3.3.2.dist-info/entry_points.txt
amirispy-3.3.2.dist-info/licenses/LICENSES/Apache-2.0.txt
amirispy-3.3.2.dist-info/licenses/LICENSES/CC-BY-4.0.txt
amirispy-3.3.2.dist-info/licenses/LICENSES/CC0-1.0.txt
amirispy-3.3.2.dist-info/METADATA
amirispy-3.3.2.dist-info/WHEEL
amirispy-3.3.2.dist-info/RECORD
