Metadata-Version: 2.4
Name: amirispy
Version: 3.3.2
Summary: Python tools for the open electricity market model AMIRIS
License-Expression: Apache-2.0
License-File: LICENSES/Apache-2.0.txt
License-File: LICENSES/CC-BY-4.0.txt
License-File: LICENSES/CC0-1.0.txt
Keywords: AMIRIS,agent-based modelling,electricity market
Author: Christoph Schimeczek
Author-email: amiris@dlr.de
Maintainer: Christoph Schimeczek
Maintainer-email: amiris@dlr.de
Requires-Python: >=3.9,<4.0
Classifier: Development Status :: 5 - Production/Stable
Classifier: Environment :: Console
Classifier: Intended Audience :: Science/Research
Classifier: Operating System :: OS Independent
Classifier: Programming Language :: Python :: 3
Classifier: Programming Language :: Python :: 3.9
Classifier: Programming Language :: Python :: 3.10
Classifier: Programming Language :: Python :: 3.11
Classifier: Programming Language :: Python :: 3.12
Classifier: Programming Language :: Python :: 3.13
Classifier: Programming Language :: Python :: 3.14
Classifier: Topic :: Scientific/Engineering
Requires-Dist: fameio (>=3.5.2,<4.0)
Requires-Dist: wget (>=3.2,<4.0)
Project-URL: Changelog, https://gitlab.com/dlr-ve/esy/amiris/amiris-py/-/blob/main/CHANGELOG.md
Project-URL: Homepage, https://helmholtz.software/software/amiris
Project-URL: Issue Tracking, https://gitlab.com/dlr-ve/esy/amiris/amiris-py/-/issues
Project-URL: Repository, https://gitlab.com/dlr-ve/esy/amiris/amiris-py
